pyapprox/__init__.py
pyapprox/analysis/__init__.py
pyapprox/analysis/active_subspace.py
pyapprox/analysis/convergence_studies.py
pyapprox/analysis/parameter_sweeps.py
pyapprox/analysis/sensitivity_analysis.py
pyapprox/analysis/visualize.py
pyapprox/analysis/tests/__init__.py
pyapprox/analysis/tests/test_active_subspace.py
pyapprox/analysis/tests/test_parameter_sweeps.py
pyapprox/analysis/tests/test_sensitivity_analysis.py
pyapprox/bayes/__init__.py
pyapprox/bayes/gaussian_network.py
pyapprox/bayes/hmc.py
pyapprox/bayes/laplace.py
pyapprox/bayes/metropolis.py
pyapprox/bayes/tests/__init__.py
pyapprox/bayes/tests/test_gaussian_network.py
pyapprox/bayes/tests/test_laplace.py
pyapprox/bayes/tests/test_metropolis.py
pyapprox/benchmarks/__init__.py
pyapprox/benchmarks/benchmarks.py
pyapprox/benchmarks/genz.py
pyapprox/benchmarks/multifidelity_benchmarks.py
pyapprox/benchmarks/pde_benchmarks.py
pyapprox/benchmarks/sensitivity_benchmarks.py
pyapprox/benchmarks/surrogate_benchmarks.py
pyapprox/benchmarks/tests/__init__.py
pyapprox/benchmarks/tests/test_benchmarks.py
pyapprox/benchmarks/tests/test_genz.py
pyapprox/benchmarks/tests/test_multifidelity_benchmarks.py
pyapprox/benchmarks/tests/test_pde_benchmarks.py
pyapprox/cython/__init__.py
pyapprox/cython/adaptive_sparse_grid.cpython-38-darwin.so
pyapprox/cython/barycentric_interpolation.cpython-38-darwin.so
pyapprox/cython/function_train.cpython-38-darwin.so
pyapprox/cython/manipulate_polynomials.cpython-38-darwin.so
pyapprox/cython/multivariate_polynomials.cpython-38-darwin.so
pyapprox/cython/orthonormal_polynomials_1d.cpython-38-darwin.so
pyapprox/cython/sparse_grid.cpython-38-darwin.so
pyapprox/cython/univariate_quadrature.cpython-38-darwin.so
pyapprox/cython/utilities.cpython-38-darwin.so
pyapprox/expdesign/__init__.py
pyapprox/expdesign/bayesian_oed.py
pyapprox/expdesign/linear_oed.py
pyapprox/expdesign/low_discrepancy_sequences.py
pyapprox/expdesign/tests/__init__.py
pyapprox/expdesign/tests/test_bayesian_oed.py
pyapprox-1.0.3.dist-info/LICENSE
pyapprox-1.0.3.dist-info/METADATA
pyapprox-1.0.3.dist-info/WHEEL
pyapprox-1.0.3.dist-info/top_level.txt
pyapprox-1.0.3.dist-info/RECORD
