Metadata-Version: 2.1
Name: pyapprox
Version: 1.0.3
Summary: High-dimensional function approximation and estimation
Home-page: https://github.com/sandialabs/pyapprox
Author: John D. Jakeman
Author-email: "John D. Jakeman" <29109026+jdjakem@users.noreply.github.com>
License: Copyright 2019 National Technology & Engineering Solutions of Sandia, LLC (NTESS). Under the terms of Contract DE-NA0003525 with NTESS, the U.S. Government retains certain rights in this software.
Classifier: Programming Language :: Python :: 3
Classifier: License :: OSI Approved :: MIT License
Classifier: Operating System :: OS Independent
Requires-Python: >=3.7
License-File: LICENSE
Requires-Dist: numpy >=1.16.4
Requires-Dist: matplotlib
Requires-Dist: scipy >=1.0.0
Requires-Dist: Cython
Requires-Dist: sympy
Requires-Dist: torch
Requires-Dist: scikit-learn
Requires-Dist: coverage >=6.4
Requires-Dist: pytest-cov
Requires-Dist: pytest >=4.6
Requires-Dist: networkx
Requires-Dist: numba
Requires-Dist: scikit-fem
Requires-Dist: umbridge
Provides-Extra: docs
Requires-Dist: numpydoc ; extra == 'docs'
Requires-Dist: sphinx ; extra == 'docs'
Requires-Dist: sphinx-automodapi ; extra == 'docs'
Requires-Dist: sphinx-rtd-theme ; extra == 'docs'
Requires-Dist: sphinx-gallery ; extra == 'docs'
Requires-Dist: jupyter ; extra == 'docs'
